sclitr/__init__.py
sclitr/datasets.py
sclitr/pl.py
sclitr/pp.py
sclitr/tl.py
sclitr/utils.py
sclitr-1.0.1.dist-info/METADATA
sclitr-1.0.1.dist-info/WHEEL
sclitr-1.0.1.dist-info/top_level.txt
sclitr-1.0.1.dist-info/RECORD
